opensslpy/__init__.py
opensslpy/asym.py
opensslpy/sym.py
opensslpy-0.0.2.dist-info/LICENSE
opensslpy-0.0.2.dist-info/METADATA
opensslpy-0.0.2.dist-info/WHEEL
opensslpy-0.0.2.dist-info/top_level.txt
opensslpy-0.0.2.dist-info/RECORD
